portage-stubs/__init__.pyi
portage-stubs/dbapi/__init__.pyi
portage-stubs/dbapi/porttree.pyi
portage-stubs/package/__init__.pyi
portage-stubs/package/ebuild/__init__.pyi
portage-stubs/package/ebuild/config.pyi
portage-stubs/package/ebuild/doebuild.pyi
portage-stubs/versions.pyi
portage_stubs-0.0.7.dist-info/METADATA
portage_stubs-0.0.7.dist-info/WHEEL
portage_stubs-0.0.7.dist-info/licenses/LICENSE.txt
portage_stubs-0.0.7.dist-info/RECORD
