Metadata-Version: 2.4
Name: portage-stubs
Version: 0.0.7
Summary: PEP 561 type stubs for portage.
License-Expression: MIT
License-File: LICENSE.txt
Keywords: gentoo,pep561,portage,stubs,types
Author: Andrew Udvare
Author-email: audvare@gmail.com
Requires-Python: >=3.10,<4.0
Classifier: Development Status :: 4 - Beta
Classifier: Intended Audience :: Developers
Classifier: Programming Language :: Python
Classifier: Programming Language :: Python :: 3.10
Classifier: Programming Language :: Python :: 3.11
Classifier: Programming Language :: Python :: 3.12
Classifier: Programming Language :: Python :: 3.13
Classifier: Programming Language :: Python :: 3.14
Classifier: Typing :: Stubs Only
Requires-Dist: typing-extensions (>=4.15.0,<5.0.0)
Project-URL: Documentation, https://portage-stubs.readthedocs.org
Project-URL: Homepage, https://tatsh.github.io/portage-stubs/
Project-URL: Issues, https://github.com/Tatsh/portage-stubs/issues
Project-URL: Repository, https://github.com/Tatsh/portage-stubs
